thalesians/__init__.py
thalesians/tsvc/__init__.py
thalesians/tsvc/deltas.py
thalesians/tsvc/caches/__init__.py
thalesians/tsvc/caches/in_memory_cache.py
thalesians/tsvc/caches/pickle_cache.py
thalesians/tsvc/delta_logs/__init__.py
thalesians/tsvc/delta_logs/in_memory_delta_log.py
thalesians/tsvc/delta_logs/pickle_delta_log.py
thalesians/tsvc/meta_data/__init__.py
thalesians/tsvc/meta_data/dict_meta_data.py
thalesians/tsvc/meta_data_caches/__init__.py
thalesians/tsvc/meta_data_caches/in_memory_meta_data_cache.py
thalesians/tsvc/meta_data_caches/pickle_meta_data_cache.py
thalesians/tsvc/revision_caches/__init__.py
thalesians/tsvc/revision_caches/in_memory_revision_cache.py
thalesians/tsvc/revision_caches/pickle_revision_cache.py
thalesians/tsvc/store/__init__.py
thalesians/tsvc/store/pickle_store.py
thalesians/tsvc/ts_impls/__init__.py
thalesians/tsvc/ts_impls/pandas_ts_impl.py
thalesians/tsvc/ts_impls/polars_ts_impl.py
thalesians/tsvc/vc/__init__.py
thalesians_tsvc-0.0.1.dist-info/licenses/LICENSE
thalesians_tsvc-0.0.1.dist-info/METADATA
thalesians_tsvc-0.0.1.dist-info/WHEEL
thalesians_tsvc-0.0.1.dist-info/top_level.txt
thalesians_tsvc-0.0.1.dist-info/RECORD
