Metadata-Version: 2.4
Name: thalesians.tsvc
Version: 0.0.1
Summary: A lightweight, efficient version control system specifically designed for time series data
Author-email: Paul Alexander Bilokon <paul@thalesians.com>
Project-URL: Homepage, https://github.com/thalesians/tsvc/
Project-URL: Issues, https://github.com/thalesians/tsvc/issues
Classifier: Programming Language :: Python :: 3
Classifier: License :: OSI Approved :: Apache Software License
Classifier: Operating System :: OS Independent
Requires-Python: >=3.12
License-File: LICENSE
Requires-Dist: numpy>=1.26.4
Requires-Dist: pandas>=2.2.3
Dynamic: license-file
